yaya/__init__.py
yaya/__main__.py
yaya/byte_ops.py
yaya/converter.py
yaya/document.py
yaya/emitter.py
yaya/extract.py
yaya/formatting.py
yaya/modifications.py
yaya/nodes.py
yaya/path.py
yaya/serialization.py
lossless_yaml-0.3.0.dist-info/METADATA
lossless_yaml-0.3.0.dist-info/WHEEL
lossless_yaml-0.3.0.dist-info/licenses/LICENSE
lossless_yaml-0.3.0.dist-info/RECORD
