Metadata-Version: 2.4
Name: lossless-yaml
Version: 0.3.0
Summary: Yet Another YAML AST - programmatically transform YAML, preserving whitespace and comments
Project-URL: Homepage, https://github.com/Open-Athena/yaya
Project-URL: Repository, https://github.com/Open-Athena/yaya
Author-email: Ryan Williams <ryan@no.de>
License: MIT
License-File: LICENSE
Keywords: ast,editor,formatting,lossless,round-trip,transformer,yaml
Classifier: Development Status :: 3 - Alpha
Classifier: Intended Audience :: Developers
Classifier: License :: OSI Approved :: MIT License
Classifier: Programming Language :: Python :: 3
Classifier: Programming Language :: Python :: 3.10
Classifier: Programming Language :: Python :: 3.11
Classifier: Programming Language :: Python :: 3.12
Classifier: Programming Language :: Python :: 3.13
Classifier: Topic :: Software Development :: Libraries :: Python Modules
Classifier: Topic :: Text Processing :: Markup
Requires-Python: >=3.10
Requires-Dist: ruamel-yaml>=0.17.0
